flask_ldapauth/__init__.py
Flask_LDAPAuth-0.0.3.dist-info/METADATA
Flask_LDAPAuth-0.0.3.dist-info/WHEEL
Flask_LDAPAuth-0.0.3.dist-info/entry_points.txt
Flask_LDAPAuth-0.0.3.dist-info/top_level.txt
Flask_LDAPAuth-0.0.3.dist-info/RECORD
