Metadata-Version: 2.1
Name: Flask-LDAPAuth
Version: 0.0.3
Summary: List url link, script tags, reponse headers
Home-page: https://github.com/null011/Flask-LDAPAuth.git
Author: Noe Macias
Author-email: notnull011@gmail.com
License: UNKNOWN
Project-URL: Bug Tracker, https://github.com/null011/Flask-LDAPAuth.git/issues
Platform: UNKNOWN
Classifier: Programming Language :: Python :: 3
Classifier: License :: OSI Approved :: MIT License
Classifier: Operating System :: OS Independent
Requires-Python: >=3.6
Requires-Dist: Flask
Requires-Dist: PyJWT
Requires-Dist: python-ldap
